{"working_dir":null,"default_chunk_options":{"echo":true},"chunk_definitions":[{"row":9,"row_count":1,"visible":true,"expansion_state":0,"options":{"engine":"r","label":"setup","include":false},"document_id":"84B9078D","chunk_id":"csetup_chunk","chunk_label":"setup"},{"row":16,"row_count":1,"visible":true,"expansion_state":0,"options":{"engine":"r","label":"unnamed-chunk-1"},"document_id":"84B9078D","chunk_id":"csrsqfvthbj5v","chunk_label":"unnamed-chunk-1"},{"row":67,"row_count":1,"visible":true,"expansion_state":0,"options":{"engine":"r","label":"unnamed-chunk-34"},"document_id":"84B9078D","chunk_id":"cnxdoeg6yatef","chunk_label":"unnamed-chunk-2"},{"row":116,"row_count":1,"visible":true,"expansion_state":0,"options":{"engine":"r","label":"unnamed-chunk-58"},"document_id":"84B9078D","chunk_id":"cgtkuwzj9vv8x","chunk_label":"unnamed-chunk-4"},{"row":134,"row_count":1,"visible":true,"expansion_state":0,"options":{"engine":"r","label":"unnamed-chunk-74"},"document_id":"84B9078D","chunk_id":"cqsxxhoc7tf1x","chunk_label":"unnamed-chunk-5"}],"doc_write_time":1667333891,"chunk_rendered_width":700}